yieldlang/__init__.py
yieldlang/generator.py
yieldlang/py.typed
yieldlang/types.py
yieldlang/utils.py
yieldlang/version.py
yieldlang-0.1.1.dist-info/LICENSE
yieldlang-0.1.1.dist-info/METADATA
yieldlang-0.1.1.dist-info/WHEEL
yieldlang-0.1.1.dist-info/top_level.txt
yieldlang-0.1.1.dist-info/RECORD
