Metadata-Version: 2.1
Name: yieldlang
Version: 0.1.1
Author-email: HK-SHAO <hk-shao@outlook.com>
License: GNU GENERAL PUBLIC LICENSE
Project-URL: Homepage, https://github.com/yieldlang/yieldlang
Project-URL: Repository, https://github.com/yieldlang/yieldlang
Project-URL: Changelog, https://github.com/yieldlang/yieldlang/blob/main/docs/source/CHANGELOG.md
Classifier: Intended Audience :: Science/Research
Classifier: Development Status :: 3 - Alpha
Classifier: License :: OSI Approved :: Apache Software License
Classifier: Programming Language :: Python :: 3
Classifier: Topic :: Scientific/Engineering :: Artificial Intelligence
Requires-Python: >=3.8
License-File: LICENSE
Provides-Extra: dev
Requires-Dist: ruff ; extra == 'dev'
Requires-Dist: mypy <1.11,>=1.0 ; extra == 'dev'
Requires-Dist: black <25.0,>=23.0 ; extra == 'dev'
Requires-Dist: isort <5.14,>=5.12 ; extra == 'dev'
Requires-Dist: pytest ; extra == 'dev'
Requires-Dist: pytest-sphinx ; extra == 'dev'
Requires-Dist: pytest-cov ; extra == 'dev'
Requires-Dist: twine >=1.11.0 ; extra == 'dev'
Requires-Dist: build ; extra == 'dev'
Requires-Dist: setuptools ; extra == 'dev'
Requires-Dist: wheel ; extra == 'dev'
Requires-Dist: Sphinx <7.4.0,>=4.3.0 ; extra == 'dev'
Requires-Dist: furo ==2024.4.27 ; extra == 'dev'
Requires-Dist: myst-parser <3.1,>=1.0 ; extra == 'dev'
Requires-Dist: sphinx-copybutton ==0.5.2 ; extra == 'dev'
Requires-Dist: sphinx-autobuild ==2021.3.14 ; extra == 'dev'
Requires-Dist: sphinx-autodoc-typehints ==2.0.1 ; extra == 'dev'
Requires-Dist: sphinx-autoapi ; extra == 'dev'
Requires-Dist: packaging ; extra == 'dev'
